pydsboilerplates/__init__.py
pydsboilerplates/linkedlist.py
pydsboilerplates/tree.py
pydsboilerplates/utils.py
pydsboilerplates-0.1.2.dist-info/licenses/LICENSE
pydsboilerplates-0.1.2.dist-info/METADATA
pydsboilerplates-0.1.2.dist-info/WHEEL
pydsboilerplates-0.1.2.dist-info/top_level.txt
pydsboilerplates-0.1.2.dist-info/RECORD
