Metadata-Version: 2.4
Name: pydsboilerplates
Version: 0.1.2
Summary: A Python library of classic data structures like LinkedList, Tree, and more.
Author-email: Ashay Katrojwar <ashaykatrojwar12@gmail.com>
License: MIT
Project-URL: Source, https://github.com/Ashay-20/pydsboilerplates
Project-URL: Issues, https://github.com/Ashay-20/pydsboilerplates/issues
Classifier: Programming Language :: Python :: 3
Classifier: License :: OSI Approved :: MIT License
Classifier: Operating System :: OS Independent
Classifier: Topic :: Software Development :: Libraries
Requires-Python: >=3.8
License-File: LICENSE
Dynamic: license-file
